{
  "contracts": [
    {
      "id": "1",
      "ContractCode": "1",
      "ContractDescription": "trtqw",
      "SORTitle": "retre",
      "DefaultQuestionSet": "trtr",
      "ListName": "rtrt",
      "InvoiceType": "trtt",
      "RententionPercentage": "ttt",
      "RetentionPeriod": "tt",
      "PlannedMaintenance": "rty",
      "JobComplete": "ytryty",
      "StatusCode": "yyyyy",
      "StartDate": "10-11-2017",
      "EndDate": "10-12-2017",
      "Owner": "eff",
      "Origin": "ffffff",
      "ChargeType": "fffff"
    },
    {
      "id": "2",
      "ContractCode": "2",
      "ContractDescription": "trtqw",
      "SORTitle": "retre",
      "DefaultQuestionSet": "trtr",
      "ListName": "rtrt",
      "InvoiceType": "trtt",
      "RententionPercentage": "ttt",
      "RetentionPeriod": "tt",
      "PlannedMaintenance": "rty",
      "JobComplete": "ytryty",
      "StatusCode": "yyyyy",
      "StartDate": "10-11-2017",
      "EndDate": "10-12-2017",
      "Owner": "eff",
      "Origin": "ffffff",
      "ChargeType": "fffff"
    },
    {
      "id": "3",
      "ContractCode": "3",
      "ContractDescription": "trtqw",
      "SORTitle": "retre",
      "DefaultQuestionSet": "trtr",
      "ListName": "rtrt",
      "InvoiceType": "trtt",
      "RententionPercentage": "ttt",
      "RetentionPeriod": "tt",
      "PlannedMaintenance": "rty",
      "JobComplete": "ytryty",
      "StatusCode": "yyyyy",
      "StartDate": "10-11-2017",
      "EndDate": "10-12-2017",
      "Owner": "eff",
      "Origin": "ffffff",
      "ChargeType": "fffff"
    },
    {
      "ContractCode": "bbv",
      "ContractDescription": "vbb",
      "SORTitle": "vcbvb",
      "DefaultQuestionSet": "",
      "InvoiceType": "",
      "RententionPercentage": "bvbvb",
      "RetentionPeriod": "",
      "PlannedMaintenance": "",
      "JobComplete": "",
      "StatusCode": "",
      "StartDate": "",
      "EndDate": "",
      "Owner": "",
      "Origin": "",
      "ChargeType": "vbvbb",
      "id": "rkkEkb-aW"
    },
    {
      "ContractCode": "vcbvc",
      "ContractDescription": "bbvbbn",
      "SORTitle": "vbvcbb",
      "DefaultQuestionSet": "",
      "InvoiceType": "vbvb",
      "RententionPercentage": "vbbb",
      "RetentionPeriod": "bbb",
      "PlannedMaintenance": "",
      "JobComplete": "",
      "StatusCode": "",
      "StartDate": "bb",
      "EndDate": "bvbvb",
      "Owner": "",
      "Origin": "",
      "ChargeType": "",
      "id": "rkkEkb-aW1"
    },
    {
      "ContractCode": "xzxz",
      "ContractDescription": "xxcxc",
      "SORTitle": "xcxcc",
      "DefaultQuestionSet": "CONS - Responsive repairs & planned maintenance",
      "InvoiceType": "xxxxxxxxxxx",
      "RententionPercentage": "cccccccccc",
      "ListName": "2014A - Catchup Servicing - 99",
      "RetentionPeriod": "cccccccccccccccccccc",
      "PlannedMaintenance": "",
      "JobComplete": "",
      "StatusCode": "LIVE - Live",
      "StartDate": "2017-10-17T18:30:00.000Z",
      "EndDate": "2017-10-18T18:30:00.000Z",
      "Owner": "Client",
      "Origin": "",
      "ChargeType": "ccccccccccc",
      "id": "rkkEkb-aW11"
    },
    {
      "ContractCode": "xvvv",
      "ContractDescription": "cxvcvc",
      "SORTitle": "cvcvcx",
      "DefaultQuestionSet": "CONS - Responsive repairs & planned maintenance",
      "InvoiceType": "xvcvcvcv",
      "RententionPercentage": "cvvvvvvvvvv",
      "ListName": "2014A - Catchup Servicing - 99",
      "RetentionPeriod": "vvvvvvvvvvv",
      "PlannedMaintenance": "",
      "JobComplete": "",
      "StatusCode": "",
      "StartDate": "2017-10-18T18:30:00.000Z",
      "EndDate": "2017-10-24T18:30:00.000Z",
      "Owner": "Client",
      "Origin": "MOBC - Open mobile",
      "ChargeType": "cxvvvvvvvvvvvv",
      "id": "Hyq5xX-6Z"
    },
    {
      "ContractCode": "dfdfdf",
      "ContractDescription": "dffdf",
      "SORTitle": "dfdff",
      "DefaultQuestionSet": "CONS - Responsive repairs & planned maintenance",
      "InvoiceType": "dfdfd",
      "RententionPercentage": "cxcxc",
      "ListName": "2014A - Catchup Servicing - 99",
      "RetentionPeriod": "cxcxcx",
      "PlannedMaintenance": "",
      "JobComplete": "",
      "StatusCode": "",
      "StartDate": "2017-10-23T18:30:00.000Z",
      "EndDate": "",
      "Owner": "Client",
      "Origin": "MOBC - Open mobile",
      "ChargeType": "fffffff",
      "id": "BJJcimWa-"
    },
    {
      "id": "H1Z3gVbaZ"
    },
    {
      "ContractCode": "vvcv",
      "ContractDescription": "cvcv",
      "SORTitle": "ccccccccccc",
      "DefaultQuestionSet": "CONS - Responsive repairs & planned maintenance",
      "InvoiceType": "cxvcvcv",
      "RententionPercentage": "cvcv",
      "ListName": "2014A - Catchup Servicing - 99",
      "RetentionPeriod": "cvccvc",
      "PlannedMaintenance": "",
      "JobComplete": "",
      "StatusCode": "DEAD - Dead",
      "StartDate": "2017-10-16T18:30:00.000Z",
      "EndDate": "2017-10-16T18:30:00.000Z",
      "Owner": "Shared",
      "Origin": "MOBC - Open mobile",
      "ChargeType": "cccccccc",
      "id": "B1tGuJG6b"
    },
    {
      "ContractCode": "svdsv",
      "ContractDescription": "dvfdvfd",
      "SORTitle": "vfdvfdv",
      "DefaultQuestionSet": "CONS - Responsive repairs & planned maintenance",
      "InvoiceType": "vdvfvf",
      "RententionPercentage": "dvdvdv",
      "ListName": "AGASS - Annual gas service north view - 1",
      "RetentionPeriod": "dvdv",
      "PlannedMaintenance": "",
      "JobComplete": "",
      "StatusCode": "",
      "StartDate": "2017-10-15T18:30:00.000Z",
      "EndDate": "",
      "Owner": "Shared",
      "Origin": "MOBC - Open mobile",
      "ChargeType": "xzczxz",
      "id": "SJeYRQ76-"
    },
    {
      "ContractCode": "zccx",
      "ContractDescription": "xcxcx",
      "SORTitle": "xvcv",
      "DefaultQuestionSet": "CONS - Responsive repairs & planned maintenance",
      "InvoiceType": "cvcxvcx",
      "RententionPercentage": "cvcvc",
      "ListName": "AGASS - Annual gas service north view - 1",
      "RetentionPeriod": "cvcvc",
      "PlannedMaintenance": "",
      "JobComplete": "",
      "StatusCode": "",
      "StartDate": "2017-10-16T18:30:00.000Z",
      "EndDate": "2017-10-16T18:30:00.000Z",
      "Owner": "Shared",
      "Origin": "MOBC - Open mobile",
      "ChargeType": "csddfd",
      "id": "rynjR7XT-"
    },
    {
      "ContractCode": "zccx",
      "ContractDescription": "xcxcx",
      "SORTitle": "xvcv",
      "DefaultQuestionSet": "CONS - Responsive repairs & planned maintenance",
      "InvoiceType": "cvcxvcx",
      "RententionPercentage": "cvcvc",
      "ListName": "AGASS - Annual gas service north view - 1",
      "RetentionPeriod": "cvcvc",
      "PlannedMaintenance": "",
      "JobComplete": "",
      "StatusCode": "",
      "StartDate": "2017-10-16T18:30:00.000Z",
      "EndDate": "2017-10-16T18:30:00.000Z",
      "Owner": "Shared",
      "Origin": "MOBC - Open mobile",
      "ChargeType": "csddfd",
      "id": "SkAjRmmTW"
    }
  ]
}